<!--
theme name:     Mighty Orb
version         1.0
-->

<?xml version="1.0" encoding="UTF-8"?>
<theme>
   <formatVersion>4</formatVersion>

<feature supported="carousel">

   <view name="system">
      <carousel name="systemcarousel">
        <type>horizontal</type>
        <pos>0 -0.39</pos>
        <size>1 1</size>
        <logoScale>1.14</logoScale>
        <logoSize>0.36 0.45</logoSize>
        <color>00000000</color>
        <maxLogoCount>3</maxLogoCount>
        <zIndex>41</zIndex>
        <logoAlignment>bottom</logoAlignment>                      
      </carousel>     
 
       <image name="background" extra="true">
         <origin>0 0</origin>
         <pos>0 0</pos>
         <size>1 1</size>
         <path>./_inc/images/backdrop.png</path>
         <zIndex>40</zIndex>
      </image>
      
       <image name="background2" extra="true">
         <origin>0 0</origin>
         <pos>0 0</pos>
         <size>1 1</size>
         <path>./_inc/images/maintop.png</path>
         <zIndex>43</zIndex>
      </image>      
           
      <text name="systemInfo">
         <pos>0.0 0.555</pos>
         <backgroundColor>00000000</backgroundColor>
         <color>ffffff</color>
         <fontPath>./_inc/fonts/impact.ttf</fontPath>
	     <fontSize>0.015</fontSize>
      </text>
      
      <helpsystem name="help">
         <pos>0.31 0.972</pos>
         <fontPath>./_inc/fonts/Space Quest.ttf</fontPath>          
	     <fontSize>0.017</fontSize>              
         <textColor>ffffff</textColor>
         <iconColor>ffffff</iconColor>
      </helpsystem>      
      
   </view>
</feature>


  <view name="video">
      <textlist name="gamelist">
         <pos>0.64 0.0195</pos>
         <size>0.35 0.637</size>
         <selectorColor>1c1c1c00</selectorColor>
         <selectedColor>4EAFEA</selectedColor>
         <primaryColor>ffffff</primaryColor>
         <secondaryColor>ffffff</secondaryColor>
         <fontPath>./_inc/fonts/Space Quest.ttf</fontPath>
         <fontSize>0.049</fontSize>
         <forceUppercase>1</forceUppercase>
         <scrollSound></scrollSound>
         <zIndex>44</zIndex>         
         <alignment>left</alignment>
      </textlist>
      <image name="background" extra="true">
         <origin>0 0</origin>
         <pos>0 0</pos>
         <size>1 1</size>
         <path>./_inc/images/backdrop.png</path>
         <zIndex>40</zIndex>         
      </image>
      <image name="background2" extra="true">
         <origin>0 0</origin>
         <pos>0 0</pos>
         <size>1 1</size>
         <path>./_inc/images/systemtop.png</path>
         <zIndex>42</zIndex>         
      </image>
      <text name="md_lbl_rating, md_lbl_releasedate, md_lbl_developer, md_lbl_publisher, md_lbl_genre, md_lbl_lastplayed, md_lbl_playcount, md_rating, md_developer, md_publisher, md_genre, md_playcount, md_lastplayed">
         <pos>1 1</pos>
      </text>
      <text name="md_lbl_rating,md_lbl_releasedate, md_lbl_developer, md_lbl_publisher, md_lbl_genre, md_lbl_lastplayed, md_lbl_playcount,md_lbl_players,md_developer, md_publisher, md_genre, md_playcount, md_lastplayed,md_description,md_players,md_releasedate">
         <color>0C1777</color>
         <fontPath>./_inc/fonts/Space Quest.ttf</fontPath>
         <fontSize>0.0195</fontSize>
      </text>
      <rating name="md_rating">
         <pos>0.378 0.72</pos>
         <size>0.12 0.06</size>
         <filledPath>./_inc/images/star_filled.png</filledPath>
         <unfilledPath>./_inc/images/star_empty.png</unfilledPath>
         <zIndex>44</zIndex>          
      </rating>
      <text name="md_lbl_players">
         <pos>0.272 0.14</pos>
         <size>0.1 0.035</size>
         <zIndex>44</zIndex>          
      </text>
      <text name="md_players">
         <pos>0.345 0.14</pos>
         <size>0.1 0.035</size>
         <color>ffffff</color>
         <zIndex>44</zIndex>                   
      </text>
      <text name="md_lbl_releasedate">
         <pos>0.272 0.166</pos>
         <size>0.1 0.035</size>
         <zIndex>44</zIndex>          
      </text>
      <datetime name="md_releasedate">
         <pos>0.36 0.166</pos>
         <size>0.1 0.035</size>
         <color>ffffff</color>         
         <zIndex>44</zIndex> 
      </datetime>
      <text name="md_lbl_genre">
         <pos>0.272 0.192</pos>
         <size>0.1 0.035</size>
         <zIndex>44</zIndex>          
      </text>
      <text name="md_genre">
         <pos>0.33 0.204</pos>
         <size>0.15 0.01</size>
         <color>ffffff</color>
         <zIndex>44</zIndex>                   
      </text>
      <text name="md_lbl_playcount">
         <pos>0.272 0.218</pos>
         <size>0.1 0.035</size>
         <zIndex>44</zIndex>          
      </text>
      <text name="md_playcount">
         <pos>0.39 0.230</pos>
         <size>0.12 0.01</size>
         <color>ffffff</color>
         <zIndex>44</zIndex>                   
      </text>      
      <text name="md_description">
         <pos>0.64 0.71</pos>
         <size>0.33 0.26</size>
         <color>ffffff</color>
         <zIndex>44</zIndex>          
      </text>
      <video name="md_video">
         <origin>0.5 0.5</origin>
         <pos>0.47 0.52</pos>
         <maxSize>0.3 0.3</maxSize>
         <delay>1.0</delay>
         <showSnapshotNoVideo>true</showSnapshotNoVideo>
         <showSnapshotDelay>true</showSnapshotDelay>
         <zIndex>41</zIndex>          
      </video>
      <image name="md_marquee">
         <pos>0.373 0.09</pos>
         <origin>0.5 0.5</origin>
         <maxSize>0.12 0.12</maxSize>
         <zIndex>44</zIndex>         
      </image>
      <helpsystem name="help">
         <pos>0.08 0.97</pos>
         <fontPath>./_inc/fonts/Space Quest.ttf</fontPath>          
	     <fontSize>0.017</fontSize>              
         <textColor>ffffff</textColor>
         <iconColor>ffffff</iconColor>
      </helpsystem>            
  </view>

  <view name="detailed">
      <textlist name="gamelist">
         <pos>0.64 0.0195</pos>
         <size>0.35 0.637</size>
         <selectorColor>1c1c1c00</selectorColor>
         <selectedColor>4EAFEA</selectedColor>
         <primaryColor>ffffff</primaryColor>
         <secondaryColor>ffffff</secondaryColor>
         <fontPath>./_inc/fonts/Space Quest.ttf</fontPath>
         <fontSize>0.049</fontSize>
         <forceUppercase>1</forceUppercase>
         <scrollSound></scrollSound>
         <zIndex>44</zIndex>         
         <alignment>left</alignment>
      </textlist>
      <image name="background" extra="true">
         <origin>0 0</origin>
         <pos>0 0</pos>
         <size>1 1</size>
         <path>./_inc/images/backdrop.png</path>
         <zIndex>40</zIndex>         
      </image>
      <image name="background2" extra="true">
         <origin>0 0</origin>
         <pos>0 0</pos>
         <size>1 1</size>
         <path>./_inc/images/systemtop.png</path>
         <zIndex>42</zIndex>         
      </image>
      <text name="md_lbl_rating, md_lbl_releasedate, md_lbl_developer, md_lbl_publisher, md_lbl_genre, md_lbl_lastplayed, md_lbl_playcount, md_rating, md_developer, md_publisher, md_genre, md_playcount, md_lastplayed">
         <pos>1 1</pos>
      </text>
      <text name="md_lbl_rating,md_lbl_releasedate, md_lbl_developer, md_lbl_publisher, md_lbl_genre, md_lbl_lastplayed, md_lbl_playcount,md_lbl_players,md_developer, md_publisher, md_genre, md_playcount, md_lastplayed,md_description,md_players,md_releasedate">
         <color>0C1777</color>
         <fontPath>./_inc/fonts/Space Quest.ttf</fontPath>
         <fontSize>0.0195</fontSize>
      </text>
      <rating name="md_rating">
         <pos>0.378 0.72</pos>
         <size>0.12 0.06</size>
         <filledPath>./_inc/images/star_filled.png</filledPath>
         <unfilledPath>./_inc/images/star_empty.png</unfilledPath>
         <zIndex>44</zIndex>          
      </rating>
      <text name="md_lbl_players">
         <pos>0.272 0.07</pos>
         <size>0.1 0.035</size>
         <zIndex>44</zIndex>          
      </text>
      <text name="md_players">
         <pos>0.345 0.07</pos>
         <size>0.1 0.035</size>
         <color>ffffff</color>
         <zIndex>44</zIndex>                   
      </text>
      <text name="md_lbl_releasedate">
         <pos>0.272 0.117</pos>
         <size>0.1 0.035</size>
         <zIndex>44</zIndex>          
      </text>
      <datetime name="md_releasedate">
         <pos>0.36 0.117</pos>
         <size>0.1 0.035</size>
         <color>ffffff</color>         
         <zIndex>44</zIndex> 
      </datetime>
      <text name="md_lbl_genre">
         <pos>0.272 0.162</pos>
         <size>0.1 0.035</size>
         <zIndex>44</zIndex>          
      </text>
      <text name="md_genre">
         <pos>0.33 0.174</pos>
         <size>0.15 0.01</size>
         <color>ffffff</color>
         <zIndex>44</zIndex>                   
      </text>
      <text name="md_lbl_playcount">
         <pos>0.272 0.208</pos>
         <size>0.1 0.035</size>
         <zIndex>44</zIndex>          
      </text>
      <text name="md_playcount">
         <pos>0.39 0.22</pos>
         <size>0.12 0.01</size>
         <color>ffffff</color>
         <zIndex>44</zIndex>                   
      </text>      
      <text name="md_description">
         <pos>0.64 0.71</pos>
         <size>0.33 0.26</size>
         <color>ffffff</color>
         <zIndex>44</zIndex>          
      </text>  
      <image name="md_image">
         <origin>0.5 0.5</origin>
         <pos>0.47 0.52</pos>
         <maxSize>0.3 0.3</maxSize>
         <zIndex>41</zIndex>          
      </image>      
      <helpsystem name="help">
         <pos>0.08 0.97</pos>
         <fontPath>./_inc/fonts/Space Quest.ttf</fontPath>          
	     <fontSize>0.017</fontSize>              
         <textColor>ffffff</textColor>
         <iconColor>ffffff</iconColor>
      </helpsystem>             
  </view>


  <view name="basic">
      <textlist name="gamelist">
         <pos>0.64 0.0195</pos>
         <size>0.35 0.96</size>
         <selectorColor>1c1c1c00</selectorColor>
         <selectedColor>4EAFEA</selectedColor>
         <primaryColor>ffffff</primaryColor>
         <secondaryColor>ffffff</secondaryColor>
         <fontPath>./_inc/fonts/Space Quest.ttf</fontPath>
         <fontSize>0.049</fontSize>
         <forceUppercase>1</forceUppercase>
         <scrollSound></scrollSound>
         <zIndex>44</zIndex>         
         <alignment>left</alignment>
      </textlist>
      <image name="background" extra="true">
         <origin>0 0</origin>
         <pos>0 0</pos>
         <size>1 1</size>
         <path>./_inc/images/backdrop.png</path>
         <zIndex>40</zIndex>         
      </image>
      <image name="background2" extra="true">
         <origin>0 0</origin>
         <pos>0 0</pos>
         <size>1 1</size>
         <path>./_inc/images/systemtopb.png</path>
         <zIndex>42</zIndex>         
      </image>             
      <helpsystem name="help">
         <pos>0.08 0.97</pos>
         <fontPath>./_inc/fonts/Space Quest.ttf</fontPath>          
	     <fontSize>0.017</fontSize>              
         <textColor>ffffff</textColor>
         <iconColor>ffffff</iconColor>
      </helpsystem>             
  </view>
   
</theme>
